src/Framework.py
src/__init__.py
ammp_framework-1.0.0.dist-info/METADATA
ammp_framework-1.0.0.dist-info/WHEEL
ammp_framework-1.0.0.dist-info/licenses/LICENSE
ammp_framework-1.0.0.dist-info/RECORD
