Metadata-Version: 2.1
Name: ammp-framework
Version: 1.0.0
Summary: A Configuration Class for the AMMP Framework
Project-URL: Homepage, https://github.houston.softwaregrp.net/WW-Modernization
Project-URL: Bug Tracker, https://github.houston.softwaregrp.net/WW-Modernization/issues
Author-email: Markus von der Heiden <mvonderheide@opentext.com>
License-File: LICENSE
Classifier: License :: OSI Approved :: MIT License
Classifier: Operating System :: OS Independent
Classifier: Programming Language :: Python :: 3
Requires-Python: >=3.10
